dj_beat_drop/__init__.py
dj_beat_drop/main_cli.py
dj_beat_drop/new.py
dj_beat_drop/py.typed
dj_beat_drop/utils.py
dj_beat_drop/templates/4.2/manage.py-tpl
dj_beat_drop/templates/4.2/project_name/__init__.py-tpl
dj_beat_drop/templates/4.2/project_name/asgi.py-tpl
dj_beat_drop/templates/4.2/project_name/settings.py-tpl
dj_beat_drop/templates/4.2/project_name/urls.py-tpl
dj_beat_drop/templates/4.2/project_name/wsgi.py-tpl
dj_beat_drop/templates/5.1/manage.py-tpl
dj_beat_drop/templates/5.1/project_name/__init__.py-tpl
dj_beat_drop/templates/5.1/project_name/asgi.py-tpl
dj_beat_drop/templates/5.1/project_name/settings.py-tpl
dj_beat_drop/templates/5.1/project_name/urls.py-tpl
dj_beat_drop/templates/5.1/project_name/wsgi.py-tpl
dj_beat_drop/templates/5.2/manage.py-tpl
dj_beat_drop/templates/5.2/project_name/__init__.py-tpl
dj_beat_drop/templates/5.2/project_name/asgi.py-tpl
dj_beat_drop/templates/5.2/project_name/settings.py-tpl
dj_beat_drop/templates/5.2/project_name/urls.py-tpl
dj_beat_drop/templates/5.2/project_name/wsgi.py-tpl
dj_beat_drop-0.6.0.dist-info/METADATA
dj_beat_drop-0.6.0.dist-info/WHEEL
dj_beat_drop-0.6.0.dist-info/entry_points.txt
dj_beat_drop-0.6.0.dist-info/licenses/LICENSE
dj_beat_drop-0.6.0.dist-info/RECORD
