Metadata-Version: 2.4
Name: dj-beat-drop
Version: 0.6.0
Summary: Add your description here
Project-URL: Homepage, https://github.com/epicserve/dj-beat-drop
Project-URL: Source, https://github.com/epicserve/dj-beat-drop
Project-URL: Documentation, https://github.com/epicserve/dj-beat-drop
License-File: LICENSE
Classifier: Development Status :: 3 - Alpha
Classifier: Framework :: Django
Classifier: Intended Audience :: Developers
Classifier: License :: OSI Approved :: GNU General Public License v3 (GPLv3)
Classifier: Operating System :: OS Independent
Classifier: Programming Language :: Python
Classifier: Programming Language :: Python :: 3
Classifier: Programming Language :: Python :: 3.11
Classifier: Programming Language :: Python :: 3.12
Classifier: Topic :: Software Development :: Build Tools
Classifier: Topic :: Software Development :: Libraries :: Application Frameworks
Requires-Python: >=3.10
Requires-Dist: inquirerpy>=0.3.4
Requires-Dist: packaging>=24.1
Requires-Dist: requests>=2.32.3
Requires-Dist: setuptools>=75.1.0
Requires-Dist: typer>=0.12.5
Requires-Dist: uv>=0.4.26
